{
  "type": "FeatureCollection",
  "features": [
    {
      "type": "Feature",
      "geometry": {
        "type": "Point",
        "coordinates": [
          5.30603,
          51.65831
        ]
      },
      "properties": {
        "marker-symbol": "marker",
        "name": "Kasteel Maurik",
        "address": "Maurik 3, 5261 NA Vught, Netherlands"
      }
    }
  ]
}
